llamachat/__init__.py
llamachat/_version.py
llamachat/app.py
llamachat/cli.py
llamachat/utils.py
llamachat-0.1.1.dist-info/METADATA
llamachat-0.1.1.dist-info/WHEEL
llamachat-0.1.1.dist-info/entry_points.txt
llamachat-0.1.1.dist-info/top_level.txt
llamachat-0.1.1.dist-info/RECORD
