Metadata-Version: 2.1
Name: llamachat
Version: 0.1.1
Requires-Dist: streamlit
Requires-Dist: llama-index
Requires-Dist: langsmith
Requires-Dist: ragas
Requires-Dist: click
